celery_utils/__init__.py
celery_utils/admin.py
celery_utils/apps.py
celery_utils/logged_task.py
celery_utils/models.py
celery_utils/persist_on_failure.py
celery_utils/tasks.py
celery_utils/management/__init__.py
celery_utils/management/commands/__init__.py
celery_utils/management/commands/cleanup_resolved_tasks.py
celery_utils/management/commands/reapply_tasks.py
celery_utils/management/commands/tests/__init__.py
celery_utils/management/commands/tests/test_cleanup_resolved_tasks.py
celery_utils/management/commands/tests/test_reapply_tasks.py
celery_utils/migrations/0001_initial.py
celery_utils/migrations/0002_chordable_django_backend.py
celery_utils/migrations/0003_rename_failedtask_task_name_exc_idx_failedtask_task_exc.py
celery_utils/migrations/__init__.py
edx_celeryutils-1.4.0.dist-info/licenses/AUTHORS
edx_celeryutils-1.4.0.dist-info/licenses/LICENSE.txt
edx_celeryutils-1.4.0.dist-info/METADATA
edx_celeryutils-1.4.0.dist-info/WHEEL
edx_celeryutils-1.4.0.dist-info/top_level.txt
edx_celeryutils-1.4.0.dist-info/RECORD
