Metadata-Version: 2.4
Name: edx-celeryutils
Version: 1.4.0
Summary: Code to support working with celery
Home-page: https://github.com/openedx/edx-celeryutils
Author: edX
Author-email: oscm@edx.org
License: Apache 2.0
Keywords: Django edx
Classifier: Development Status :: 3 - Alpha
Classifier: Framework :: Django
Classifier: Framework :: Django :: 4.2
Classifier: Intended Audience :: Developers
Classifier: License :: OSI Approved :: Apache Software License
Classifier: Natural Language :: English
Classifier: Programming Language :: Python :: 3
Classifier: Programming Language :: Python :: 3.11
Classifier: Programming Language :: Python :: 3.12
Classifier: Framework :: Django :: 4.2
Classifier: Framework :: Django :: 5.2
License-File: LICENSE.txt
License-File: AUTHORS
Requires-Dist: Django
Requires-Dist: celery<6.0
Requires-Dist: django-model-utils
Requires-Dist: jsonfield
Dynamic: author
Dynamic: author-email
Dynamic: classifier
Dynamic: description
Dynamic: home-page
Dynamic: keywords
Dynamic: license
Dynamic: license-file
Dynamic: requires-dist
Dynamic: summary
